MANIFEST.in
README.rst
setup.cfg
setup.py
ckanext/__init__.py
ckanext/datastore_ts/__init__.py
ckanext/datastore_ts/commands.py
ckanext/datastore_ts/controller.py
ckanext/datastore_ts/db.py
ckanext/datastore_ts/helpers.py
ckanext/datastore_ts/interfaces.py
ckanext/datastore_ts/plugin.py
ckanext/datastore_ts/controller/__init__.py
ckanext/datastore_ts/controller/resource_controller.py
ckanext/datastore_ts/examples/create.json
ckanext/datastore_ts/fanstatic/datastore_resource.js
ckanext/datastore_ts/fanstatic/datastore_ts_popover.js
ckanext/datastore_ts/logic/__init__.py
ckanext/datastore_ts/logic/action.py
ckanext/datastore_ts/logic/auth.py
ckanext/datastore_ts/logic/schema.py
ckanext/datastore_ts/templates/package/snippets/datastore_fields.html
ckanext/datastore_ts/templates/package/snippets/resource_edit_form.html
ckanext/datastore_ts/templates/package/snippets/resource_form.html
ckanext/datastore_ts/templates/snippets/package_item.html
ckanext/datastore_ts/tests/__init__.py
ckanext/datastore_ts/tests/helpers.py
ckanext/datastore_ts/tests/resetdb.py
ckanext/datastore_ts/tests/sample_datastore_plugin.py
ckanext/datastore_ts/tests/skipped_test_dump.py
ckanext/datastore_ts/tests/skipped_test_interface.py
ckanext/datastore_ts/tests/test_commands.py
ckanext/datastore_ts/tests/test_create.py
ckanext/datastore_ts/tests/test_create_short.py
ckanext/datastore_ts/tests/test_db.py
ckanext/datastore_ts/tests/test_delete.py
ckanext/datastore_ts/tests/test_dump.py
ckanext/datastore_ts/tests/test_helpers.py
ckanext/datastore_ts/tests/test_info.py
ckanext/datastore_ts/tests/test_plugin.py
ckanext/datastore_ts/tests/test_retention.py
ckanext/datastore_ts/tests/test_search.py
ckanext/datastore_ts/tests/test_search_short.py
ckanext/datastore_ts/tests/test_search_timeseries.py
ckanext/datastore_ts/tests/test_unit.py
ckanext/datastore_ts/tests/test_upsert.py
ckanext/datastore_ts/tests/test_upsert_short.py
ckanext_datastore_ts.egg-info/PKG-INFO
ckanext_datastore_ts.egg-info/SOURCES.txt
ckanext_datastore_ts.egg-info/dependency_links.txt
ckanext_datastore_ts.egg-info/entry_points.txt
ckanext_datastore_ts.egg-info/pbr.json
ckanext_datastore_ts.egg-info/requires.txt
ckanext_datastore_ts.egg-info/top_level.txt