Metadata-Version: 1.1
Name: ckanext-datastore-ts
Version: 0.1.1
Summary: Timeseries-based datastore extension
Home-page: https://github.com/namgk/ckanext-datastore_ts
Author: Nam Giang
Author-email: kyng@ece.ubc.ca
License: AGPL
Keywords: CKAN
Platform: UNKNOWN
Classifier: Development Status :: 4 - Beta
Classifier: License :: OSI Approved :: GNU Affero General Public License v3 or later (AGPLv3+)
Classifier: Programming Language :: Python :: 2.6
Classifier: Programming Language :: Python :: 2.7
